find_homework_yuketang/__main__.py
find_homework_yuketang/main.py
find_homework_yuketang/tool.py
find_homework_yuketang-0.1.0.dist-info/METADATA
find_homework_yuketang-0.1.0.dist-info/WHEEL
find_homework_yuketang-0.1.0.dist-info/entry_points.txt
find_homework_yuketang-0.1.0.dist-info/top_level.txt
find_homework_yuketang-0.1.0.dist-info/RECORD
